strats/__init__.py
strats/py.typed
strats/api/__init__.py
strats/api/middleware.py
strats/api/router.py
strats/api/server.py
strats/cmd/__init__.py
strats/cmd/clock.py
strats/cmd/cmd.py
strats/cmd/common.py
strats/cmd/monitors.py
strats/cmd/runserver.py
strats/cmd/strategy.py
strats/core/__init__.py
strats/core/clock.py
strats/core/data.py
strats/core/kernel.py
strats/core/lifecycle.py
strats/core/monitor.py
strats/core/state.py
strats/core/strategy.py
strats/internal/__init__.py
strats/internal/log_config.py
strats/internal/lru_set.py
strats/model/__init__.py
strats/model/prices.py
strats/monitor/__init__.py
strats/monitor/cron_monitor.py
strats/monitor/static_monitor.py
strats/monitor/stream_monitor.py
strats-0.1.13.dist-info/METADATA
strats-0.1.13.dist-info/WHEEL
strats-0.1.13.dist-info/entry_points.txt
strats-0.1.13.dist-info/licenses/LICENSE
strats-0.1.13.dist-info/RECORD
